huaweicloudsdkdataartsstudio/__init__.py
huaweicloudsdkdataartsstudio/v1/__init__.py
huaweicloudsdkdataartsstudio/v1/dataartsstudio_async_client.py
huaweicloudsdkdataartsstudio/v1/dataartsstudio_client.py
huaweicloudsdkdataartsstudio/v1/model/__init__.py
huaweicloudsdkdataartsstudio/v1/model/accept_security_application_request.py
huaweicloudsdkdataartsstudio/v1/model/accept_security_application_response.py
huaweicloudsdkdataartsstudio/v1/model/account_permission.py
huaweicloudsdkdataartsstudio/v1/model/add_design_entity_tags_request.py
huaweicloudsdkdataartsstudio/v1/model/add_design_entity_tags_response.py
huaweicloudsdkdataartsstudio/v1/model/add_tag_to_asset_request.py
huaweicloudsdkdataartsstudio/v1/model/add_tag_to_asset_response.py
huaweicloudsdkdataartsstudio/v1/model/add_work_space_users_request.py
huaweicloudsdkdataartsstudio/v1/model/add_work_space_users_response.py
huaweicloudsdkdataartsstudio/v1/model/advanced_mall_api_dto.py
huaweicloudsdkdataartsstudio/v1/model/aggregation_logic_table_attribute_vo.py
huaweicloudsdkdataartsstudio/v1/model/aggregation_logic_table_vo.py
huaweicloudsdkdataartsstudio/v1/model/aggregation_logic_table_vo_detail_data.py
huaweicloudsdkdataartsstudio/v1/model/aggregation_logic_table_vo_search_result_data.py
huaweicloudsdkdataartsstudio/v1/model/aggregation_logic_table_vo_search_result_data_value.py
huaweicloudsdkdataartsstudio/v1/model/alarm_info_response_alarm_info.py
huaweicloudsdkdataartsstudio/v1/model/alarm_period.py
huaweicloudsdkdataartsstudio/v1/model/alarm_rules_items_details.py
huaweicloudsdkdataartsstudio/v1/model/algorithm_detail_dto.py
huaweicloudsdkdataartsstudio/v1/model/all_model_statistic_vo.py
huaweicloudsdkdataartsstudio/v1/model/all_table_vo.py
huaweicloudsdkdataartsstudio/v1/model/api.py
huaweicloudsdkdataartsstudio/v1/model/api_action_dto.py
huaweicloudsdkdataartsstudio/v1/model/api_catalog_create_para_dto.py
huaweicloudsdkdataartsstudio/v1/model/api_catalog_delete_para_dto.py
huaweicloudsdkdataartsstudio-3.1.184.dist-info/METADATA
huaweicloudsdkdataartsstudio-3.1.184.dist-info/WHEEL
huaweicloudsdkdataartsstudio-3.1.184.dist-info/licenses/LICENSE
huaweicloudsdkdataartsstudio-3.1.184.dist-info/RECORD
